docforest/__init__.py
docforest/enums.py
docforest/main.py
docforest-0.1.1.dist-info/licenses/LICENSE
docforest-0.1.1.dist-info/METADATA
docforest-0.1.1.dist-info/WHEEL
docforest-0.1.1.dist-info/top_level.txt
docforest-0.1.1.dist-info/RECORD
