Metadata-Version: 2.4
Name: docforest
Version: 0.1.1
Summary: A package for intelligently chunking structured documents into a hierarchical, contextual tree.
Author-email: Yuseok William Kang <willysk73@outlook.com>
Project-URL: Homepage, https://github.com/willysk73/docforest
Project-URL: Issues, https://github.com/willysk73/docforest/issues
Classifier: Programming Language :: Python :: 3
Classifier: License :: OSI Approved :: MIT License
Classifier: Operating System :: OS Independent
Requires-Python: >=3.9
License-File: LICENSE
Dynamic: license-file
